{"q+DBL6Ip/DUrNNhuYzaAOQ==":"mbr.jpg","gsjYRdHRUVZKKoL5D2DVIg==":"mbr.jpeg","Jvd/Hv+E6dzGxsxf1OSMGw==":"mbr-1.jpg","Rkh6VN1geuklqasa+Hps8w==":"mbr-2.jpg","OgtCKla7ZhzAplY/dXMFRQ==":"mbr-3.jpg","7cAX25vTViPzsEpxKtfgnw==":"mbr-4.jpg","Bzg68IuBcRh9sFO8XLZmEQ==":"mbr-5.jpg","3L8x5ialuZVROWzapuz4nA==":"mbr-6.jpg","5Yxz1Ro3xgEvJK27QZYsvA==":"mbr-1.jpeg","orRrDp0O7uYYPUWXMASTrg==":"mbr-2.jpeg","hNnJ/ah4jJ+gnKLIjKCM+Q==":"mbr-3.jpeg","8lvp9ISHPOav0iH8GHzE5A==":"mbr-596x397.jpg","RvxaV1cdrF4bi647UYR4rA==":"screenshot-2026-01-13.png","FgG7/TL2k/lCmM8xUkyhTw==":"screenshot-2026-01-14.png","oCoVALfjLndYr5qwap9xtA==":"screenshot%25202026-01-13%2520142832-208x264.png","NQh1HcyrdRePNaRAozjr5Q==":"screenshot%25202026-01-13%2520143217-385x394.png","ayg5+9MLcpwsIdQu6c/5jQ==":"screenshot%25202026-01-13%2520143202-234x276.png","AFv96UQErHA4+ZkXZOIfFw==":"mbr-596x335.jpg","5YUXaR4xYPR9LQfo7qQgnQ==":"mbr-596x421.jpg","sCf1GXtqTwfVu8NZRB83Zg==":"mbr-596x398.jpg","W3kQsg+YcNcXTaUs3lUyjg==":"mbr-596x337.jpg","v2nXYcHi+ufVWIcAkhkz9Q==":"screenshot%25202026-01-13%2520142133-477x694.png","V1Ug6GoXVSsIeSui0kHugQ==":"screenshot%25202026-01-13%2520142228-367x472.png","JKF08YrkDCWRXlnauQ662w==":"mbr-1256x705.jpg","sPs5M+qW6NKoe5Ytmps0+w==":"screenshot%25202026-01-18%2520191347-400x281.png","lr2miteRfd7ZPliosmu8HA==":"screenshot%25202026-01-18%2520191534-93x136.png","Vi0E38uQ/O0BZwaNubgQgQ==":"4-720x360.jpg","rnfzlDn6tm6JDonC9QDfDQ==":"screenshot%25202026-01-18%2520191347-543x381.png"}